almgroad/__init__.py
almgroad/chat.py
almgroad/info_tik.py
almgroad/infoinsta.py
almgroad/insta.py
almgroad/ktkt.py
almgroad/pryer.py
almgroad/restinsta.py
almgroad/search_pinterset.py
almgroad/soundcloud.py
almgroad/tik_tok.py
almgroad/twitter.py
almgroad/youtu.py
almgroad-9.1.1.dist-info/METADATA
almgroad-9.1.1.dist-info/WHEEL
almgroad-9.1.1.dist-info/top_level.txt
almgroad-9.1.1.dist-info/RECORD
