Metadata-Version: 2.1
Name: almgroad
Version: 9.1.1
Summary: UNKNOWN
Home-page: UNKNOWN
Author: Ibrahim Mohammed
Author-email: ibrahom0780@gmail.com
License: MIT
Platform: UNKNOWN
Classifier: Programming Language :: Python :: 3
Classifier: License :: OSI Approved :: MIT License
Classifier: Operating System :: OS Independent
Requires-Dist: bs4
Requires-Dist: pytube
Requires-Dist: requests
